eyja_filedb/__init__.py
eyja_filedb/client.py
eyja_filedb/config.py
eyja_filedb/db/__init__.py
eyja_filedb/db/connection.py
eyja_filedb/db/db.py
eyja_filedb/db/db_batch.py
eyja_filedb/db/table.py
tests/__init__.py
tests/test_client.py
eyja_filedb-0.1.0.dist-info/METADATA
eyja_filedb-0.1.0.dist-info/WHEEL
eyja_filedb-0.1.0.dist-info/top_level.txt
eyja_filedb-0.1.0.dist-info/zip-safe
eyja_filedb-0.1.0.dist-info/RECORD
